graph_z/__init__.py
graph_z/graph_z.py
graph_z_c-0.1.2.dist-info/METADATA
graph_z_c-0.1.2.dist-info/WHEEL
graph_z_c-0.1.2.dist-info/top_level.txt
graph_z_c-0.1.2.dist-info/RECORD
