Metadata-Version: 2.1
Name: graph-z-c
Version: 0.1.2
Summary: Structures to play with graphs
Home-page: UNKNOWN
License: UNKNOWN
Platform: UNKNOWN
